src/__init__.py
testing/__init__.py
testing/unit_tests.py
test_cicd_pipeline-0.6.0.dist-info/LICENSE
test_cicd_pipeline-0.6.0.dist-info/METADATA
test_cicd_pipeline-0.6.0.dist-info/WHEEL
test_cicd_pipeline-0.6.0.dist-info/top_level.txt
test_cicd_pipeline-0.6.0.dist-info/RECORD
