Metadata-Version: 2.1
Name: test-cicd-pipeline
Version: 0.6.0
Summary: Package to setup and test basic CICD pipeline
Home-page: https://github.com/Maarten-s1991/testcicd
Author: UNKNOWN
Author-email: maarten.s1991@gmail.com
License: UNKNOWN
Platform: UNKNOWN
